agents_sdk_models/__init__.py
agents_sdk_models/anthropic.py
agents_sdk_models/clearify_agent.py
agents_sdk_models/context.py
agents_sdk_models/flow.py
agents_sdk_models/gemini.py
agents_sdk_models/gen_agent.py
agents_sdk_models/llm.py
agents_sdk_models/llm_pipeline.py
agents_sdk_models/message.py
agents_sdk_models/ollama.py
agents_sdk_models/pipeline.py
agents_sdk_models/py.typed
agents_sdk_models/step.py
agents_sdk_models/tracing.py
agents_sdk_models-0.0.23.dist-info/METADATA
agents_sdk_models-0.0.23.dist-info/WHEEL
agents_sdk_models-0.0.23.dist-info/licenses/LICENSE
agents_sdk_models-0.0.23.dist-info/RECORD
