Metadata-Version: 2.4
Name: agents-sdk-models
Version: 0.0.23
Summary: Model adapters for OpenAI Agents SDK
Project-URL: Homepage, https://github.com/kitfactory/agents-sdk-models
Project-URL: Documentation, https://kitfactory.github.io/agents-sdk-models/
Project-URL: Repository, https://github.com/kitfactory/agents-sdk-models
Project-URL: Bug-Tracker, https://github.com/kitfactory/agents-sdk-models/issues
License-File: LICENSE
Requires-Python: >=3.9
Requires-Dist: colorama>=0.4.6
Requires-Dist: httpx>=0.28.1
Requires-Dist: mkdocstrings>=0.29.1
Requires-Dist: openai-agents>=0.0.6
Requires-Dist: openai>=1.68.0
Requires-Dist: pydantic<3,>=2.10
